AniMAIRE/AniMAIRE.py
AniMAIRE/AniMAIRE_event.py
AniMAIRE/DoseRateFrame.py
AniMAIRE/MAIREPLUS_event.py
AniMAIRE/MAIREPLUS_spectrum.py
AniMAIRE/__init__.py
AniMAIRE/dose_plotting.py
AniMAIRE/utils.py
AniMAIRE/anisotropic_MAIRE_engine/AsymptoticDirectionProcessing.py
AniMAIRE/anisotropic_MAIRE_engine/__init__.py
AniMAIRE/anisotropic_MAIRE_engine/generalEngineInstance.py
AniMAIRE/anisotropic_MAIRE_engine/otso_cone_processing.py
AniMAIRE/anisotropic_MAIRE_engine/otso_planet_processing.py
AniMAIRE/anisotropic_MAIRE_engine/singleParticleEngineInstance.py
AniMAIRE/anisotropic_MAIRE_engine/data/NM64_alpha_response_tabulated_2013.csv
AniMAIRE/anisotropic_MAIRE_engine/data/NM64_alpha_response_tabulated_2020.csv
AniMAIRE/anisotropic_MAIRE_engine/data/NM64_proton_response.csv
AniMAIRE/anisotropic_MAIRE_engine/data/NM64_proton_response_tabulated_2013.csv
AniMAIRE/anisotropic_MAIRE_engine/data/NM64_responses.py
AniMAIRE/anisotropic_MAIRE_engine/data/__init__.py
AniMAIRE/anisotropic_MAIRE_engine/rigidityPredictor/__init__.py
AniMAIRE/anisotropic_MAIRE_engine/rigidityPredictor/rigidity_predictor.py
AniMAIRE/anisotropic_MAIRE_engine/rigidityPredictor/data/cutoff_rigidity_predictor.pkl
AniMAIRE/anisotropic_MAIRE_engine/spectralCalculations/__init__.py
AniMAIRE/anisotropic_MAIRE_engine/spectralCalculations/momentaDistribution.py
AniMAIRE/anisotropic_MAIRE_engine/spectralCalculations/particleDistribution.py
AniMAIRE/anisotropic_MAIRE_engine/spectralCalculations/particleSpecies.py
AniMAIRE/anisotropic_MAIRE_engine/spectralCalculations/pitchAngleDistribution.py
AniMAIRE/anisotropic_MAIRE_engine/spectralCalculations/rigiditySpectrum.py
AniMAIRE/anisotropic_MAIRE_engine/spectralCalculations/utils.py
AniMAIRE/maire_plus_tools/__init__.py
AniMAIRE/maire_plus_tools/calculate_MAIREPLUS_spectral_index.py
AniMAIRE/maire_plus_tools/calculate_spectral_index.py
AniMAIRE/maire_plus_tools/example.py
AniMAIRE/maire_plus_tools/neutron_monitor.py
animaire-1.4.1.dist-info/licenses/LICENCE
pytests/__init__.py
animaire-1.4.1.dist-info/METADATA
animaire-1.4.1.dist-info/WHEEL
animaire-1.4.1.dist-info/top_level.txt
animaire-1.4.1.dist-info/RECORD
