Metadata-Version: 2.4
Name: AniMAIRE
Version: 1.4.1
Summary: Python library for running the anisotropic version of MAIRE+
Home-page: https://github.com/ssc-maire/AniMAIRE-public
Author: Space Environment and Protection Group, University of Surrey
License: CC By-NC-SA 4.0
Keywords: anisotropic MAIRE+ atmospheric ionizing radiation dose rates cosmic rays ground level enhancements GLEs protons alpha particles neutrons effective ambient equivalent aircraft aviation Earth solar system sun space magnetic field
License-File: LICENCE
Requires-Dist: numpy>=1.21.6
Requires-Dist: pandarallel>=1.6.3
Requires-Dist: pandas>=1.3.5
Requires-Dist: ParticleRigidityCalculationTools>=1.5.4
Requires-Dist: scipy>=1.7.3
Requires-Dist: setuptools>=45.2.0
Requires-Dist: spacepy>=0.3.0
Requires-Dist: tqdm>=4.65.0
Requires-Dist: plotly>=5.9.0
Requires-Dist: numba>=0.57.1
Requires-Dist: metpy>=1.5.1
Requires-Dist: CosRayModifiedISO>=1.2.9
Requires-Dist: AsympDirsCalculator>=1.0.8
Requires-Dist: seaborn>=0.13.2
Requires-Dist: geopandas>=0.11.1
Requires-Dist: joblib>=1.2.0
Requires-Dist: spaceweather>=0.2.4
Requires-Dist: atmosphericRadiationDoseAndFlux>=1.0.3
Requires-Dist: kpindex>=2.0.0
Requires-Dist: ipywidgets>=8.1.5
Requires-Dist: dask>=2022.0.0
Requires-Dist: pyarrow>=12.0.0
Requires-Dist: matplotlib>=3.10.1
Requires-Dist: cartopy>=0.22.0
Requires-Dist: netCDF4>=1.7.2
Requires-Dist: imageio>=2.37.0
Requires-Dist: psutil>=7.0.0
Requires-Dist: OTSO>=1.0.16
Requires-Dist: geopy>=2.0.0
Requires-Dist: pynverse>=0.1.4.6
Requires-Dist: xgboost>=1.6.0
Dynamic: author
Dynamic: description
Dynamic: description-content-type
Dynamic: home-page
Dynamic: keywords
Dynamic: license
Dynamic: license-file
Dynamic: requires-dist
Dynamic: summary
